{
  "app/[locale]/page.ts": {
    "Invalid locale: %{var0}": {
      "en": "Invalid locale: %{var0}",
      "ko": "Invalid locale: %{var0}_zhans",
      "zh-Hans": "Invalid locale: %{var0}",
      "zh-Hant": "Invalid locale: %{var0}",
      "vi": "Invalid locale: %{var0}",
      "es": "Invalid locale: %{var0}",
      "tr": "Invalid locale: %{var0}",
      "fr": "Invalid locale: %{var0}",
      "mark": 0,
      "_lastUsed": 1752329176372
    }
  },
  "src/app/[locale]/page.ts": {
    "Invalid locale: %{var0}": {
      "en": "Invalid locale: %{var0}",
      "ko": "Invalid locale: %{var0}",
      "zh-Hans": "Invalid locale: %{var0}",
      "zh-Hant": "Invalid locale: %{var0}",
      "vi": "Invalid locale: %{var0}",
      "es": "Configuración regional no válida: %{var0}",
      "tr": "Geçersiz yerel ayar: %{var0}",
      "fr": "Paramètre régional non valide : %{var0}",
      "mark": 0
    }
  },
  "src/app/[locale]/server-test/page.ts": {
    "Server Component I18n Test": {
      "en": "Server Component I18n Test",
      "ko": "Server Component I18n Test_hans",
      "zh-Hans": "Server Component I18n Test",
      "zh-Hant": "Server Component I18n Test",
      "vi": "Server Component I18n Test",
      "es": "Server Component I18n Test",
      "tr": "Server Component I18n Test",
      "fr": "Server Component I18n Test",
      "mark": 1,
      "_lastUsed": 1752329176372
    },
    "Auto-detected Locale": {
      "en": "Auto-detected Locale",
      "ko": "Auto-detected Locale",
      "zh-Hans": "Auto-detected Locale",
      "zh-Hant": "Auto-detected Locale",
      "vi": "Auto-detected Locale",
      "es": "Auto-detected Locale",
      "tr": "Auto-detected Locale",
      "fr": "Auto-detected Locale",
      "mark": 0,
      "_lastUsed": 1752329176372
    },
    "Detected locale:": {
      "en": "Detected locale:",
      "ko": "Detected locale:",
      "zh-Hans": "Detected locale:",
      "zh-Hant": "Detected locale:",
      "vi": "Detected locale:",
      "es": "Detected locale:",
      "tr": "Detected locale:",
      "fr": "Detected locale:",
      "mark": 0,
      "_lastUsed": 1752329176372
    },
    "Welcome message:": {
      "en": "Welcome message:",
      "ko": "Welcome message:",
      "zh-Hans": "Welcome message:",
      "zh-Hant": "Welcome message:",
      "vi": "Welcome message:",
      "es": "Welcome message:",
      "tr": "Welcome message:",
      "fr": "Welcome message:",
      "mark": 0,
      "_lastUsed": 1752329176372
    },
    "get_started_by_editing": {
      "en": "get_started_by_editing",
      "ko": "get_started_by_editing",
      "zh-Hans": "get_started_by_editing",
      "zh-Hant": "get_started_by_editing",
      "vi": "get_started_by_editing",
      "es": "get_started_by_editing",
      "tr": "get_started_by_editing",
      "fr": "get_started_by_editing",
      "mark": 0,
      "_lastUsed": 1752329176372
    },
    "Deploy button:": {
      "en": "Deploy button:",
      "ko": "Deploy button:",
      "zh-Hans": "Deploy button:",
      "zh-Hant": "Deploy button:",
      "vi": "Deploy button:",
      "es": "Deploy button:",
      "tr": "Deploy button:",
      "fr": "Deploy button:",
      "mark": 0,
      "_lastUsed": 1752329176372
    },
    "deploy_now": {
      "en": "deploy_now",
      "ko": "deploy_now",
      "zh-Hans": "deploy_now",
      "zh-Hant": "deploy_now",
      "vi": "deploy_now",
      "es": "deploy_now",
      "tr": "deploy_now",
      "fr": "deploy_now",
      "mark": 0,
      "_lastUsed": 1752329176372
    },
    "Docs link:": {
      "en": "Docs link:",
      "ko": "Docs link:",
      "zh-Hans": "Docs link:",
      "zh-Hant": "Docs link:",
      "vi": "Docs link:",
      "es": "Docs link:",
      "tr": "Docs link:",
      "fr": "Docs link:",
      "mark": 0,
      "_lastUsed": 1752329176372
    },
    "read_our_docs": {
      "en": "read_our_docs",
      "ko": "read_our_docs",
      "zh-Hans": "read_our_docs",
      "zh-Hant": "read_our_docs",
      "vi": "read_our_docs",
      "es": "read_our_docs",
      "tr": "read_our_docs",
      "fr": "read_our_docs",
      "mark": 0,
      "_lastUsed": 1752329176372
    },
    "Manual Locale (from route)": {
      "en": "Manual Locale (from route)",
      "ko": "Manual Locale (from route)",
      "zh-Hans": "Manual Locale (from route)",
      "zh-Hant": "Manual Locale (from route)",
      "vi": "Manual Locale (from route)",
      "es": "Manual Locale (from route)",
      "tr": "Manual Locale (from route)",
      "fr": "Manual Locale (from route)",
      "mark": 0,
      "_lastUsed": 1752329176372
    },
    "Route locale:": {
      "en": "Route locale:",
      "ko": "Route locale:",
      "zh-Hans": "Route locale:",
      "zh-Hant": "Route locale:",
      "vi": "Route locale:",
      "es": "Route locale:",
      "tr": "Route locale:",
      "fr": "Route locale:",
      "mark": 0,
      "_lastUsed": 1752329176372
    },
    "Manual locale:": {
      "en": "Manual locale:",
      "ko": "Manual locale:",
      "zh-Hans": "Manual locale:",
      "zh-Hant": "Manual locale:",
      "vi": "Manual locale:",
      "es": "Manual locale:",
      "tr": "Manual locale:",
      "fr": "Manual locale:",
      "mark": 0,
      "_lastUsed": 1752329176372
    },
    "Comparison": {
      "en": "Comparison",
      "ko": "Comparison",
      "zh-Hans": "Comparison",
      "zh-Hant": "Comparison",
      "vi": "Comparison",
      "es": "Comparison",
      "tr": "Comparison",
      "fr": "Comparison",
      "mark": 0,
      "_lastUsed": 1752329176372
    },
    "Auto vs Manual locale match:": {
      "en": "Auto vs Manual locale match:",
      "ko": "Auto vs Manual locale match:",
      "zh-Hans": "Auto vs Manual locale match:",
      "zh-Hant": "Auto vs Manual locale match:",
      "vi": "Auto vs Manual locale match:",
      "es": "Auto vs Manual locale match:",
      "tr": "Auto vs Manual locale match:",
      "fr": "Auto vs Manual locale match:",
      "mark": 0,
      "_lastUsed": 1752329176372
    },
    "/%{var0} /server-test": {
      "en": "/%{var0} /server-test",
      "ko": "/%{var0} /서버-테스트",
      "zh-Hans": "/%{var0} /server-test",
      "zh-Hant": "／％{var0}／伺服器測試",
      "vi": "/%{var0} /server-test",
      "es": "/%{var0} /prueba-de-servidor",
      "tr": "/%{var0} /server-test",
      "fr": "/%{var0} /server-test",
      "mark": 0,
      "_lastUsed": 1752329176372
    },
    "Back to Home": {
      "en": "Back to Home",
      "ko": "Back to Home",
      "zh-Hans": "Back to Home",
      "zh-Hant": "Back to Home",
      "vi": "Back to Home",
      "es": "Back to Home",
      "tr": "Back to Home",
      "fr": "Back to Home",
      "mark": 0,
      "_lastUsed": 1752329176372
    },
    "test translate": {
      "en": "test translate",
      "ko": "테스트 번역",
      "zh-Hans": "测试翻译",
      "zh-Hant": "測試翻譯",
      "vi": "kiểm tra dịch",
      "es": "prueba de traducción",
      "tr": "test çevirisi",
      "fr": "test de traduction",
      "mark": 0,
      "_lastUsed": 1752329176372
    },
    "test translate 1 one": {
      "en": "test translate 1 one",
      "ko": "테스트 번역 1 일(一)",
      "zh-Hans": "测试翻译 1 一",
      "zh-Hant": "測試翻譯 1 一",
      "vi": "bài kiểm tra dịch 1 một",
      "es": "prueba de traducción 1 uno",
      "tr": "test translate 1 bir",
      "fr": "test traduire 1 un",
      "mark": 0,
      "_lastUsed": 1752329176372
    },
    "test translate 1 two": {
      "en": "test translate 1 two",
      "ko": "번역 테스트 1 두 개",
      "zh-Hans": "测试翻译 1 二",
      "zh-Hant": "測試翻譯 1 兩個",
      "vi": "bài kiểm tra dịch 1 hai",
      "es": "prueba de traducción 1 dos",
      "tr": "test translate 1 two",
      "fr": "test traduire 1 deux",
      "mark": 0,
      "_lastUsed": 1752329176372
    },
    "test translate 1 three": {
      "en": "test translate 1 three",
      "ko": "테스트 번역 1 삼",
      "zh-Hans": "测试翻译 1 三",
      "zh-Hant": "測試翻譯 1 三",
      "vi": "kiểm tra dịch 1 ba",
      "es": "prueba de traducción 1 tres",
      "tr": "test tercüme 1 üç",
      "fr": "test traduire 1 trois",
      "mark": 0,
      "_lastUsed": 1752329176372
    },
    "test translate 1 four": {
      "en": "test translate 1 four",
      "ko": "테스트 번역 1 넷",
      "zh-Hans": "测试翻译 1 四",
      "zh-Hant": "測試翻譯 1 四",
      "vi": "bốn test dịch 1",
      "es": "prueba de traducción 1 cuatro",
      "tr": "test translate 1 four",
      "fr": "test traduire 1 quatre",
      "mark": 0,
      "_lastUsed": 1752329176372
    },
    "test translate 1 five": {
      "en": "test translate 1 five",
      "ko": "테스트 번역 1 다섯",
      "zh-Hans": "测试翻译 1 五",
      "zh-Hant": "測試翻譯 1 五",
      "vi": "bài kiểm tra dịch 1 năm",
      "es": "prueba de traducción 1 cinco",
      "tr": "test translate 1 five",
      "fr": "test traduire 1 cinq",
      "mark": 0,
      "_lastUsed": 1752329176372
    },
    "test translate 1 six": {
      "en": "test translate 1 six",
      "ko": "테스트 번역 1 육",
      "zh-Hans": "测试翻译 1 六",
      "zh-Hant": "測試翻譯 1 六",
      "vi": "bài kiểm tra dịch 1 sáu",
      "es": "prueba de traducción 1 seis",
      "tr": "test tercüme 1 altı",
      "fr": "test traduire 1 six",
      "mark": 0,
      "_lastUsed": 1752329176372
    },
    "test translate 1 seven": {
      "en": "test translate 1 seven",
      "ko": "테스트 번역 1 일곱",
      "zh-Hans": "测试翻译 1 七",
      "zh-Hant": "測試翻譯 1 seven",
      "vi": "kiểm tra dịch 1 bảy",
      "es": "prueba de traducción 1 siete",
      "tr": "test translate 1 yedi",
      "fr": "test de traduction 1 sept",
      "mark": 0,
      "_lastUsed": 1752329176372
    },
    "test translate 1 eight": {
      "en": "test translate 1 eight",
      "ko": "테스트 번역 1 여덟",
      "zh-Hans": "测试翻译 1 八",
      "zh-Hant": "測試翻譯 1 八",
      "vi": "dịch thử 1 tám",
      "es": "prueba de traducción 1 ocho",
      "tr": "test translate 1 eight",
      "fr": "test de traduction 1 huit",
      "mark": 0,
      "_lastUsed": 1752329176372
    },
    "test translate 1 nine": {
      "en": "test translate 1 nine",
      "ko": "테스트 번역 1 구",
      "zh-Hans": "测试翻译 1 九",
      "zh-Hant": "測試翻譯 1 九",
      "vi": "kiểm tra dịch 1 chín",
      "es": "prueba de traducción 1 nueve",
      "tr": "test tercüme 1 dokuz",
      "fr": "test traduire 1 neuf",
      "mark": 0,
      "_lastUsed": 1752329176372
    },
    "test translate 1 ten": {
      "en": "test translate 1 ten",
      "ko": "테스트 번역 1 십",
      "zh-Hans": "测试翻译 1 十",
      "zh-Hant": "測試翻譯 1 十",
      "vi": "kiểm tra dịch 1 mười",
      "es": "prueba de traducción 1 diez",
      "tr": "test çevir 1 on",
      "fr": "test traduire 1 dix",
      "mark": 0,
      "_lastUsed": 1752329176372
    },
    "test translate 1 eleven": {
      "en": "test translate 1 eleven",
      "ko": "테스트 번역 1 eleven",
      "zh-Hans": "测试翻译 1 十一",
      "zh-Hant": "測試翻譯 1 十一",
      "vi": "kiểm tra dịch 1 mười một",
      "es": "prueba de traducción 1 once",
      "tr": "test translate 1 eleven",
      "fr": "test de traduction 1 onze",
      "mark": 0,
      "_lastUsed": 1752329176372
    },
    "test translate 1 twelve": {
      "en": "test translate 1 twelve",
      "ko": "테스트 번역 1 열두 개",
      "zh-Hans": "测试翻译 1 十二",
      "zh-Hant": "測試翻譯 1 十二",
      "vi": "bài kiểm tra dịch 1 mười hai",
      "es": "prueba de traducción 1 doce",
      "tr": "test tercüme 1 oniki",
      "fr": "test traduire 1 douze",
      "mark": 0,
      "_lastUsed": 1752329176372
    },
    "test translate 1 thirteen": {
      "en": "test translate 1 thirteen",
      "ko": "테스트 번역 1 thirteen",
      "zh-Hans": "测试翻译1十三",
      "zh-Hant": "測試翻譯 1 十三",
      "vi": "kiểm tra dịch 1 thirteen",
      "es": "prueba de traducción 1 trece",
      "tr": "test tercüme 1 on üç",
      "fr": "test de traduction 1 treize",
      "mark": 0,
      "_lastUsed": 1752329176372
    },
    "test translate 1 fourteen": {
      "en": "test translate 1 fourteen",
      "ko": "테스트 번역 1 십사",
      "zh-Hans": "测试翻译 1 十四",
      "zh-Hant": "測試翻譯 1 十四",
      "vi": "kiểm tra dịch 1 mười bốn",
      "es": "prueba de traducción 1 catorce",
      "tr": "test tercüme 1 on dört",
      "fr": "test de traduction 1 quatorze",
      "mark": 0,
      "_lastUsed": 1752329176372
    },
    "test translate 1 fifteen": {
      "en": "test translate 1 fifteen",
      "ko": "테스트 번역 1 15",
      "zh-Hans": "测试翻译1十五",
      "zh-Hant": "測試翻譯 1 十五",
      "vi": "kiểm tra dịch 1 mười lăm",
      "es": "prueba de traducción 1 quince",
      "tr": "test tercüme 1 onbeş",
      "fr": "test de traduction 1 quinze",
      "mark": 0,
      "_lastUsed": 1752329176372
    },
    "fei fei": {
      "en": "fei fei",
      "ko": "페이페이",
      "zh-Hans": "菲菲",
      "zh-Hant": "飛飛",
      "vi": "phi phi",
      "es": "fei fei",
      "tr": "fei fei",
      "fr": "fei fei",
      "mark": 0
    },
    "by by": {
      "en": "by by",
      "ko": "안녕히 가세요",
      "zh-Hans": "再见",
      "zh-Hant": "再見",
      "vi": "tạm biệt",
      "es": "adiós",
      "tr": "bay bay",
      "fr": "au revoir",
      "mark": 0
    },
    "head": {
      "en": "head",
      "ko": "머리",
      "zh-Hans": "头",
      "zh-Hant": "頭部",
      "vi": "đầu",
      "es": "cabeza",
      "tr": "baş",
      "fr": "tête",
      "mark": 0
    },
    "table": {
      "en": "table",
      "ko": "테이블",
      "zh-Hans": "表格",
      "zh-Hant": "桌子",
      "vi": "bàn",
      "es": "mesa",
      "tr": "masa",
      "fr": "table",
      "mark": 0
    }
  },
  "src/components/ClientHome.ts": {
    "get_started_by_editing": {
      "en": "get_started_by_editing",
      "ko": "get_started_by_editing",
      "zh-Hans": "get_started_by_editing",
      "zh-Hant": "get_started_by_editing",
      "vi": "get_started_by_editing",
      "es": "get_started_by_editing",
      "tr": "get_started_by_editing",
      "fr": "get_started_by_editing",
      "mark": 0,
      "_lastUsed": 1752329176372
    },
    "deploy_now": {
      "en": "deploy_now",
      "ko": "deploy_now",
      "zh-Hans": "deploy_now",
      "zh-Hant": "deploy_now",
      "vi": "deploy_now",
      "es": "deploy_now",
      "tr": "deploy_now",
      "fr": "deploy_now",
      "mark": 0,
      "_lastUsed": 1752329176372
    },
    "read_our_docs": {
      "en": "read_our_docs",
      "ko": "read_our_docs",
      "zh-Hans": "read_our_docs",
      "zh-Hant": "read_our_docs",
      "vi": "read_our_docs",
      "es": "read_our_docs",
      "tr": "read_our_docs",
      "fr": "read_our_docs",
      "mark": 0,
      "_lastUsed": 1752329176372
    },
    "src/app/page.tsx": {
      "en": "src/app/page.tsx",
      "ko": "src/app/page.tsx",
      "zh-Hans": "src/app/page.tsx",
      "zh-Hant": "src/app/page.tsx",
      "vi": "src/app/page.tsx",
      "es": "src/app/page.tsx",
      "tr": "src/app/page.tsx",
      "fr": "src/app/page.tsx",
      "mark": 0,
      "_lastUsed": 1752329176372
    },
    "save_and_see_changes_instantly": {
      "en": "save_and_see_changes_instantly",
      "ko": "save_and_see_changes_instantly",
      "zh-Hans": "save_and_see_changes_instantly",
      "zh-Hant": "save_and_see_changes_instantly",
      "vi": "save_and_see_changes_instantly",
      "es": "save_and_see_changes_instantly",
      "tr": "save_and_see_changes_instantly",
      "fr": "save_and_see_changes_instantly",
      "mark": 0,
      "_lastUsed": 1752329176372
    },
    "const_test": {
      "en": "const_test",
      "ko": "const_test",
      "zh-Hans": "常量测试",
      "zh-Hant": "常數測試",
      "vi": "const_test",
      "es": "const_test",
      "tr": "const_test",
      "fr": "const_test",
      "mark": 0,
      "_lastUsed": 1752329176372
    },
    "const_test2": {
      "en": "const_test2",
      "ko": "const_test2",
      "zh-Hans": "常量测试2",
      "zh-Hant": "常數測試2",
      "vi": "const_test2",
      "es": "const_test2",
      "tr": "const_test2",
      "fr": "const_test2",
      "mark": 0,
      "_lastUsed": 1752329176372
    },
    "Current locale: %{var0}": {
      "en": "Current locale: %{var0}",
      "ko": "Current locale: %{var0}",
      "zh-Hans": "Current locale: %{var0}",
      "zh-Hant": "Current locale: %{var0}",
      "vi": "Current locale: %{var0}",
      "es": "Current locale: %{var0}",
      "tr": "Current locale: %{var0}",
      "fr": "Current locale: %{var0}",
      "mark": 0,
      "_lastUsed": 1752329176372
    },
    "Test Server Component I18n": {
      "en": "Test Server Component I18n",
      "ko": "Test Server Component I18n",
      "zh-Hans": "Test Server Component I18n",
      "zh-Hant": "Test Server Component I18n",
      "vi": "Test Server Component I18n",
      "es": "Test Server Component I18n",
      "tr": "Test Server Component I18n",
      "fr": "Test Server Component I18n",
      "mark": 0,
      "_lastUsed": 1752329176372
    },
    "learn": {
      "en": "learn",
      "ko": "learn",
      "zh-Hans": "learn",
      "zh-Hant": "learn",
      "vi": "learn",
      "es": "learn",
      "tr": "learn",
      "fr": "learn",
      "mark": 0,
      "_lastUsed": 1752329176372
    },
    "examples": {
      "en": "examples",
      "ko": "examples",
      "zh-Hans": "examples",
      "zh-Hant": "examples",
      "vi": "examples",
      "es": "examples",
      "tr": "examples",
      "fr": "examples",
      "mark": 0,
      "_lastUsed": 1752329176372
    },
    "go_to_nextjs": {
      "en": "go_to_nextjs",
      "ko": "다음 단계로 이동: Next.js",
      "zh-Hans": "前往 Next.js",
      "zh-Hant": "前往Next.js",
      "vi": "chuyển_sang_nextjs",
      "es": "ir_a_nextjs",
      "tr": "go_to_nextjs",
      "fr": "go_to_nextjs",
      "mark": 0,
      "_lastUsed": 1752329176372
    },
    "Welcome to Edgen Private Beta, anon! Drop your invite code below to unlock Alpha before everyone else.": {
      "en": "Welcome to Edgen Private Beta, anon! Drop your invite code below to unlock Alpha before everyone else.",
      "ko": "Edgen 비공개 베타에 오신 것을 환영합니다, 익명 사용자님! 아래에 초대 코드를 입력하여 모두보다 먼저 Alpha를 잠금 해제하세요.",
      "zh-Hans": "欢迎体验 Edgen测试版！在下方输入您的邀请码，以抢先解锁 Alpha！",
      "zh-Hant": "歡迎體驗 Edgen 私人測試版，匿名使用者！在下方輸入您的邀請碼，以搶先解鎖 Alpha！",
      "vi": "Chào mừng bạn đến với Edgen Private Beta, người dùng ẩn danh! Nhập mã mời của bạn dưới đây để mở khóa Alpha trước mọi người.",
      "es": "¡Bienvenido a la Beta Privada de Edgen, anónimo! Ingresa tu código de invitación abajo para desbloquear Alpha antes que todos.",
      "tr": "Edgen Özel Beta'ya hoş geldiniz, anonim! Herkesten önce Alpha'yı açmak için aşağıya davet kodunuzu girin.",
      "fr": "Welcome to Edgen Private Beta, anon! Drop your invite code below to unlock Alpha before everyone else.",
      "mark": 0,
      "_lastUsed": 1752329176372
    },
    "test_new_mark_field": {
      "en": "test_new_mark_field",
      "ko": "테스트_신규_마크_필드",
      "zh-Hans": "测试新标记字段",
      "zh-Hant": "測試新標記欄位",
      "vi": "kiểm_tra_trường_đánh_dấu_mới",
      "es": "prueba_campo_nueva_marca",
      "tr": "test_new_mark_field",
      "fr": "test_new_mark_field",
      "mark": 0,
      "_lastUsed": 1752329176372
    }
  },
  "src/components/Button/index.ts": {
    "I18n22": {
      "en": "I18n22",
      "ko": "I18n22",
      "zh-Hans": "国际化22",
      "zh-Hant": "國際化22",
      "vi": "I18n22",
      "es": "I18n22",
      "tr": "I18n22",
      "fr": "I18n22",
      "mark": 0,
      "_lastUsed": 1752329176372
    },
    "I18n5": {
      "en": "I18n5",
      "ko": "I18n5",
      "zh-Hans": "国际化5",
      "zh-Hant": "國際化5",
      "vi": "I18n5",
      "es": "I18n5",
      "tr": "I18n5",
      "fr": "I18n5",
      "mark": 0,
      "_lastUsed": 1752329176372
    },
    "I18n4": {
      "en": "I18n4",
      "ko": "I18n4",
      "zh-Hans": "国际化4",
      "zh-Hant": "國際化4",
      "vi": "I18n4",
      "es": "I18n4",
      "tr": "Yerelleştirme4",
      "fr": "I18n4",
      "mark": 0,
      "_lastUsed": 1752329176372
    }
  },
  "src/const/const.ts": {
    "sadasdad": {
      "en": "sadasdad",
      "ko": "sadasdad",
      "zh-Hans": "sadasdad",
      "zh-Hant": "sadasdad",
      "vi": "sadasdad",
      "es": "sadasdad",
      "tr": "sadasdad",
      "fr": "sadasdad",
      "mark": 0,
      "_lastUsed": 1752329176372
    },
    "bbb": {
      "en": "bbb",
      "ko": "bbb",
      "zh-Hans": "bbb",
      "zh-Hant": "bbb",
      "vi": "bbb",
      "es": "bbb",
      "tr": "bbb",
      "fr": "bbb",
      "mark": 1,
      "_lastUsed": 1752329176372
    }
  }
}
